aws_crawler/__init__.py
aws_crawler/__init__.pyi
aws_crawler/__main__.py
aws_crawler/__main__.pyi
aws_crawler/py.typed
aws_crawler-1.2.8.dist-info/METADATA
aws_crawler-1.2.8.dist-info/WHEEL
aws_crawler-1.2.8.dist-info/RECORD
